monocat/__init__.py
monocat/__metadata__.py
monocat/_http.py
monocat/actions.py
monocat/cli.py
monocat/github.py
monocat-0.5.0.dist-info/LICENSE
monocat-0.5.0.dist-info/METADATA
monocat-0.5.0.dist-info/WHEEL
monocat-0.5.0.dist-info/entry_points.txt
monocat-0.5.0.dist-info/top_level.txt
monocat-0.5.0.dist-info/RECORD
