Metadata-Version: 2.1
Name: monocat
Version: 0.5.0
Summary: monocat is a command line utility for managing GitHub releases
Home-page: https://github.com/jwilges/monocat
Author: Jeffrey Wilges
Author-email: jeffrey@wilges.com
License: BSD
Platform: UNKNOWN
Classifier: Development Status :: 4 - Beta
Classifier: Environment :: Console
Classifier: Operating System :: POSIX :: Linux
Classifier: Operating System :: MacOS :: MacOS X
Classifier: Operating System :: Microsoft :: Windows
Classifier: Programming Language :: Python :: 3.6
Classifier: Programming Language :: Python :: 3.7
Classifier: Programming Language :: Python :: 3.8
Classifier: Topic :: Software Development :: Build Tools
Classifier: Topic :: System :: Distributed Computing
Classifier: Topic :: System :: Networking
Classifier: Topic :: System :: Software Distribution
Classifier: Topic :: Utilities
Requires-Python: >=3.6
Requires-Dist: pydantic (>=1.4)
Requires-Dist: uritemplate (>=3)
Requires-Dist: urllib3
Requires-Dist: dataclasses ; python_version < "3.7"
